MANIFEST.in
README.md
VERSION
setup.cfg
setup.py
../LICENSE
../README.md
simple_health_checks/__init__.py
simple_health_checks/config.py
simple_health_checks/enums.py
simple_health_checks/health_checks.py
simple_health_checks/model.py
simple_health_checks.egg-info/PKG-INFO
simple_health_checks.egg-info/SOURCES.txt
simple_health_checks.egg-info/dependency_links.txt
simple_health_checks.egg-info/not-zip-safe
simple_health_checks.egg-info/requires.txt
simple_health_checks.egg-info/top_level.txt
simple_health_checks/resources/__init__.py
simple_health_checks/resources/base.py